setup.py
debfolder/__init__.py
debfolder/defaults.py
debfolder/git_helpers.py
debfolder/setup_helpers.py
debfolder.egg-info/PKG-INFO
debfolder.egg-info/SOURCES.txt
debfolder.egg-info/dependency_links.txt
debfolder.egg-info/entry_points.txt
debfolder.egg-info/requires.txt
debfolder.egg-info/top_level.txt