Metadata-Version: 1.0
Name: debfolder
Version: 0.1.2
Summary: A few tools for building Debian packages for Python.
Home-page: https://github.com/joshmarshall/debfolder
Author: Josh Marshall
Author-email: catchjosh@gmail.com
License: http://www.apache.org/licenses/LICENSE-2.0
Platform: UNKNOWN
